syntheseus_retro_star_benchmark/__init__.py
syntheseus_retro_star_benchmark/backward_model.py
syntheseus_retro_star_benchmark/files.py
syntheseus_retro_star_benchmark/hard_molecules.py
syntheseus_retro_star_benchmark/inventory.py
syntheseus_retro_star_benchmark/value_function.py
syntheseus_retro_star_benchmark/original_code/README.md
syntheseus_retro_star_benchmark/original_code/__init__.py
syntheseus_retro_star_benchmark/original_code/mlp_inference.py
syntheseus_retro_star_benchmark/original_code/mlp_policies.py
syntheseus_retro_star_benchmark/original_code/smiles_to_fp.py
syntheseus_retro_star_benchmark/original_code/value_mlp.py
syntheseus_retro_star_benchmark-0.1.2.dist-info/LICENSE
syntheseus_retro_star_benchmark-0.1.2.dist-info/METADATA
syntheseus_retro_star_benchmark-0.1.2.dist-info/WHEEL
syntheseus_retro_star_benchmark-0.1.2.dist-info/top_level.txt
syntheseus_retro_star_benchmark-0.1.2.dist-info/RECORD
