Metadata-Version: 2.2
Name: syntheseus-retro-star-benchmark
Version: 0.1.2
Summary: Syntheseus wrapper for retro* benchmark. 
Author: Austin Tripp
License: MIT License
Project-URL: Repository, https://github.com/AustinT/syntheseus-retro-star-benchmark
Requires-Python: >=3.7
License-File: LICENSE
Requires-Dist: torch
Requires-Dist: syntheseus
Requires-Dist: rdkit
Requires-Dist: pandas
Requires-Dist: rdchiral
